amazon_ads_api_connector/__init__.py
amazon_ads_api_connector/amazon_ads_api_connector.py
amazon_ads_api_connector/amazon_regions.py
amazon_ads_api_connector/amazon_reports.py
amazon_ads_api_connector/report_types.py
amazon_ads_api_connector-0.1.8.dist-info/LICENSE.txt 
amazon_ads_api_connector-0.1.8.dist-info/METADATA
amazon_ads_api_connector-0.1.8.dist-info/WHEEL
amazon_ads_api_connector-0.1.8.dist-info/top_level.txt
amazon_ads_api_connector-0.1.8.dist-info/RECORD
