Metadata-Version: 2.1
Name: amazon-ads-api-connector
Version: 0.1.8
Summary: API wrapper for the Amazon Ads API
Author: Markus U. Wahl
License-File: LICENSE.txt 
Requires-Dist: httpx
